odoo/addons/url_slug/LICENSE
odoo/addons/url_slug/README.rst
odoo/addons/url_slug/__init__.py
odoo/addons/url_slug/__manifest__.py
odoo/addons/url_slug/images/screen.png
odoo/addons/url_slug/models/__init__.py
odoo/addons/url_slug/models/url_slug_mixin.py
odoo/addons/url_slug/static/description/icon.png
odoo/addons/url_slug/static/description/index.html
odoo_addon_url_slug-18.0.1.0.0.dist-info/METADATA
odoo_addon_url_slug-18.0.1.0.0.dist-info/WHEEL
odoo_addon_url_slug-18.0.1.0.0.dist-info/top_level.txt
odoo_addon_url_slug-18.0.1.0.0.dist-info/RECORD
